nonebot_plugin_msgbuf/__init__.py
nonebot_plugin_msgbuf/base.py
nonebot_plugin_msgbuf/models.py
nonebot_plugin_msgbuf/platforms.py
nonebot_plugin_msgbuf/utils.py
nonebot_plugin_msgbuf-0.4.1.dist-info/LICENSE
nonebot_plugin_msgbuf-0.4.1.dist-info/METADATA
nonebot_plugin_msgbuf-0.4.1.dist-info/WHEEL
nonebot_plugin_msgbuf-0.4.1.dist-info/top_level.txt
nonebot_plugin_msgbuf-0.4.1.dist-info/RECORD
