Metadata-Version: 2.1
Name: nonebot-plugin-msgbuf
Version: 0.4.1
Summary: 适用于 NoneBot2 插件的被动消息构造集成
Author-email: HivertMoZara <worldmozara@163.com>
License: MIT
Project-URL: Homepage, https://github.com/NCBM/nonebot-plugin-msgbuf
Project-URL: Repository, https://github.com/NCBM/nonebot-plugin-msgbuf
Requires-Python: >=3.8
License-File: LICENSE
Requires-Dist: nonebot2 (>=2.0.0b1)
